nygrid/__init__.py
nygrid/allocate.py
nygrid/gen_params.py
nygrid/nygrid.py
nygrid/optimizer.py
nygrid/plots.py
nygrid/postprocessing.py
nygrid/ppc_idx.py
nygrid/preprocessing.py
nygrid/run_nygrid.py
nygrid/utils.py
nygrid-0.1.2.dist-info/LICENSE
nygrid-0.1.2.dist-info/METADATA
nygrid-0.1.2.dist-info/WHEEL
nygrid-0.1.2.dist-info/top_level.txt
nygrid-0.1.2.dist-info/RECORD
