Metadata-Version: 2.1
Name: nygrid
Version: 0.1.2
Summary: A python version of the NYgrid model
Home-page: https://github.com/boyuan276/NYgrid-python
Author: The NYgrid-python Developers
Author-email: The NYgrid-python Developers <by276@cornell.edu>
Maintainer: Bo Yuan
Maintainer-email: Bo Yuan <by276@cornell.edu>
License: MIT License
Project-URL: homepage, https://github.com/boyuan276/NYgrid-python
Keywords: Power system,Renewable energy,Optimization
Platform: Any
Classifier: Development Status :: 2 - Pre-Alpha
Classifier: Intended Audience :: Science/Research
Classifier: Topic :: Scientific/Engineering
Classifier: Programming Language :: Python :: 3 :: Only
Requires-Python: >=3.7
License-File: LICENSE
Requires-Dist: numpy
Requires-Dist: scipy
Requires-Dist: pandas
Requires-Dist: pyomo
Requires-Dist: pypower
Requires-Dist: matplotlib
Requires-Dist: openpyxl
Provides-Extra: dev
Requires-Dist: pytest; extra == "dev"
Requires-Dist: black; extra == "dev"
